Metadata-Version: 2.1
Name: mydatabase
Version: 0.1.0
Summary: Библиотека для подключения к PostgreSQL
Home-page: https://www.python.org
Author: Андрей
Author-email: andrey960123@gmail.com
Classifier: Programming Language :: Python :: 3
Classifier: License :: OSI Approved :: MIT License
Classifier: Operating System :: OS Independent
Requires-Python: >=3.6
License-File: LICENSE
Requires-Dist: psycopg2
Requires-Dist: PyQt5
